bbfmr/__init__.py
bbfmr/_version.py
bbfmr/complex_model.py
bbfmr/global_model.py
bbfmr/gui/__init__.py
bbfmr/gui/interactive_plotting.py
bbfmr/gui/widgets.py
bbfmr/measurement/__init__.py
bbfmr/measurement/loading.py
bbfmr/measurement/timedomain.py
bbfmr/measurement/vna.py
bbfmr/models/__init__.py
bbfmr/models/complex.py
bbfmr/models/coupling.py
bbfmr/models/damping.py
bbfmr/models/dispersion.py
bbfmr/models/ferromagnet.py
bbfmr/models/generic.py
bbfmr/models/susceptibility.py
bbfmr/processing/__init__.py
bbfmr/processing/filter.py
bbfmr/test/__init__.py
bbfmr/test/test_ComplexModel.py
bbfmr/test/test_Ferromagnet.py
bbfmr/test/test_FerromagnetModels.py
bbfmr/test/test_Measurement.py
bbfmr/test/test_freeEnergy.py
bbfmr/test/test_globalmodel.py
bbfmr/test/test_processing.py
pybbfmr-0.2.1.dist-info/DESCRIPTION.rst
pybbfmr-0.2.1.dist-info/METADATA
pybbfmr-0.2.1.dist-info/RECORD
pybbfmr-0.2.1.dist-info/WHEEL
pybbfmr-0.2.1.dist-info/metadata.json
pybbfmr-0.2.1.dist-info/top_level.txt
