Metadata-Version: 2.0
Name: pybbfmr
Version: 0.2.1
Summary: UNKNOWN
Home-page: https://gitlab.com/wmi/pybbfmr/
Author: Hannes Maier-Flaig
Author-email: hannes@maier-flaig.de
License: MIT
Keywords: bbfmr broadband FMR ferromagnetic resonance magnon
Platform: UNKNOWN
Classifier: Development Status :: 4 - Beta
Classifier: License :: OSI Approved :: MIT License
Classifier: Programming Language :: Python :: 3.5
Classifier: Topic :: Scientific/Engineering :: Physics
Requires-Python: >=3
Requires-Dist: lmfit
Requires-Dist: matplotlib
Requires-Dist: nptdms
Requires-Dist: numpy
